PiPocketGeiger/__init__.py
PiPocketGeiger-0.5.0.dist-info/LICENSE
PiPocketGeiger-0.5.0.dist-info/METADATA
PiPocketGeiger-0.5.0.dist-info/WHEEL
PiPocketGeiger-0.5.0.dist-info/top_level.txt
PiPocketGeiger-0.5.0.dist-info/zip-safe
PiPocketGeiger-0.5.0.dist-info/RECORD
