Metadata-Version: 2.1
Name: PiPocketGeiger
Version: 0.5.0
Summary: A library for monitoring radiation with the Radiation Watch Pocket Geiger.
Home-page: https://github.com/MonsieurV/PiPocketGeiger
Author: Yoan Tournade
Author-email: yoan@ytotech.com
License: MIT
Platform: any
License-File: LICENSE
Requires-Dist: rpi-lgpio>=0.6
Provides-Extra: dev
Requires-Dist: flake8; extra == "dev"
Requires-Dist: pylint; extra == "dev"
